python_rako/__init__.py
python_rako/__version__.py
python_rako/bridge.py
python_rako/const.py
python_rako/exceptions.py
python_rako/helpers.py
python_rako/model.py
python_rako/py.typed
python_rako_2025-0.4.4.dist-info/METADATA
python_rako_2025-0.4.4.dist-info/WHEEL
python_rako_2025-0.4.4.dist-info/licenses/LICENSE
python_rako_2025-0.4.4.dist-info/RECORD
