Metadata-Version: 2.4
Name: python-rako-2025
Version: 0.4.4
Summary: Asynchronous Python client for Rako Controls Lighting
Project-URL: Homepage, https://github.com/simonleigh/python-rako
Project-URL: Repository, https://github.com/simonleigh/python-rako
Project-URL: Issues, https://github.com/simonleigh/python-rako/issues
Author-email: Simon Leigh <simonleigh@users.noreply.github.com>
License-Expression: MIT
License-File: LICENSE
Keywords: api,async,automation,client,controls,lighting,rako
Classifier: Development Status :: 4 - Beta
Classifier: Framework :: AsyncIO
Classifier: Intended Audience :: Developers
Classifier: License :: OSI Approved :: MIT License
Classifier: Natural Language :: English
Classifier: Operating System :: OS Independent
Classifier: Programming Language :: Python
Classifier: Programming Language :: Python :: 3
Classifier: Programming Language :: Python :: 3.12
Classifier: Programming Language :: Python :: 3.13
Classifier: Topic :: Home Automation
Classifier: Topic :: Software Development :: Libraries :: Python Modules
Classifier: Typing :: Typed
Requires-Python: >=3.12
Requires-Dist: aiohttp>=3.11.12
Requires-Dist: asyncio-dgram>=2.2.0
Requires-Dist: xmltodict>=0.14.0
Provides-Extra: dev
Requires-Dist: hatch>=1.9.0; extra == 'dev'
Requires-Dist: pre-commit>=3.6.0; extra == 'dev'
Provides-Extra: test
Requires-Dist: aresponses>=3.0.0; extra == 'test'
Requires-Dist: coverage[toml]>=7.9.0; extra == 'test'
Requires-Dist: pytest-asyncio>=0.23.0; extra == 'test'
Requires-Dist: pytest-cov>=5.0.0; extra == 'test'
Requires-Dist: pytest>=8.4.0; extra == 'test'
